LanguageIdentifierPackage/LIDModel.py
LanguageIdentifierPackage/LID_mixed_model.pkl
LanguageIdentifierPackage/LSTMLID.py
LanguageIdentifierPackage/LanguageIdentifier.py
LanguageIdentifierPackage/__init__.py
LanguageIdentifierFolder-1.0.16.dist-info/METADATA
LanguageIdentifierFolder-1.0.16.dist-info/WHEEL
LanguageIdentifierFolder-1.0.16.dist-info/top_level.txt
LanguageIdentifierFolder-1.0.16.dist-info/RECORD
