Metadata-Version: 2.1
Name: LanguageIdentifierFolder
Version: 1.0.16
Summary: Language identifier based on an LSTM model
Home-page: UNKNOWN
License: MIT
Download-URL: https://pypi.org/project/LanguageIdentifier/
Keywords: Lid,LSTM,Language identifier,Language
Platform: UNKNOWN
Requires-Dist: torch
